cse355_machine_design/__init__.py
cse355_machine_design/automata/__init__.py
cse355_machine_design/automata/base.py
cse355_machine_design/automata/bbtm.py
cse355_machine_design/automata/dfa.py
cse355_machine_design/automata/dfa_old.py
cse355_machine_design/automata/nfa.py
cse355_machine_design/automata/pda.py
cse355_machine_design/errors/__init__.py
cse355_machine_design/registry/__init__.py
cse355_machine_design/util/__init__.py
cse355_machine_design-0.3.0.dist-info/METADATA
cse355_machine_design-0.3.0.dist-info/WHEEL
cse355_machine_design-0.3.0.dist-info/RECORD
