Metadata-Version: 2.1
Name: cse355-machine-design
Version: 0.3.0
Summary: Automata and Turing machine library for ASU's CSE 355.
Home-page: https://github.com/DaymudeLab/CSE355-MachineDesign
License: GPL-3.0-only
Author: Saajan Maslanka
Author-email: academia@saajanm.com
Requires-Python: >=3.10,<4.0
Classifier: License :: OSI Approved :: GNU General Public License v3 (GPLv3)
Classifier: Operating System :: OS Independent
Classifier: Programming Language :: Python :: 3
Classifier: Programming Language :: Python :: 3.10
Classifier: Programming Language :: Python :: 3.11
Classifier: Programming Language :: Python :: 3.12
Classifier: Programming Language :: Python :: 3.13
Requires-Dist: matplotlib (>=3.9.2,<4.0.0)
Requires-Dist: numpy (>=2.1.3,<3.0.0)
Requires-Dist: pandas (>=2.2.3,<3.0.0)
Requires-Dist: render-html (>=1.0.1,<2.0.0)
Project-URL: Bug Tracker, https://github.com/DaymudeLab/CSE355-MachineDesign/issues
Project-URL: Repository, https://github.com/DaymudeLab/CSE355-MachineDesign
